LICENSE
README.md
setup.py
src/pyEanGenerator/__init__.py
src/pyEanGenerator.egg-info/PKG-INFO
src/pyEanGenerator.egg-info/SOURCES.txt
src/pyEanGenerator.egg-info/dependency_links.txt
src/pyEanGenerator.egg-info/top_level.txt
src/pyEanGenerator/EanCheck/EanCheckHelper.py
src/pyEanGenerator/EanCheck/__init__.py
src/pyEanGenerator/EanCheck/_testEanCheckHelper.py
src/pyEanGenerator/EanGenerator/EanGenerator.py
src/pyEanGenerator/EanGenerator/_BarcodeRendering.py
src/pyEanGenerator/EanGenerator/__init__.py