Metadata-Version: 2.1
Name: pyEanGenerator
Version: 1.0.0
Summary: A simple package to generate EAN13 and EAN8
Home-page: https://github.com/Gegelascience/pyEanGenerator
Author: VERCHERE Rémi
Author-email: remi.verchere2@gmail.com
License: MIT
Keywords: pyEanGenerator,EAN,ean,checkdigit
Platform: UNKNOWN
Classifier: Programming Language :: Python :: 3
Classifier: License :: OSI Approved :: MIT License
Classifier: Operating System :: OS Independent
Requires-Python: >=3.6
License-File: LICENSE
